stimulus/__init__.py
stimulus/api/__init__.py
stimulus/api/api.py
stimulus/cli/__init__.py
stimulus/cli/check_model.py
stimulus/cli/compare_tensors.py
stimulus/cli/encode_csv.py
stimulus/cli/main.py
stimulus/cli/predict.py
stimulus/cli/split_csv.py
stimulus/cli/split_yaml.py
stimulus/cli/transform_csv.py
stimulus/cli/tuning.py
stimulus/core/__init__.py
stimulus/core/registry.py
stimulus/data/__init__.py
stimulus/data/encoders/__init__.py
stimulus/data/encoders/registry.py
stimulus/data/encoding/__init__.py
stimulus/data/encoding/encoders.py
stimulus/data/interface/__init__.py
stimulus/data/interface/data_config_parser.py
stimulus/data/interface/data_config_schema.py
stimulus/data/interface/data_loading.py
stimulus/data/splitters/__init__.py
stimulus/data/splitters/registry.py
stimulus/data/splitting/__init__.py
stimulus/data/splitting/splitters.py
stimulus/data/transform/__init__.py
stimulus/data/transform/registry.py
stimulus/data/transforming/__init__.py
stimulus/data/transforming/transforms.py
stimulus/debug.py
stimulus/learner/__init__.py
stimulus/learner/device_utils.py
stimulus/learner/interface/__init__.py
stimulus/learner/interface/model_config_parser.py
stimulus/learner/interface/model_schema.py
stimulus/learner/optuna_tune.py
stimulus/learner/predict.py
stimulus/py.typed
stimulus/typing/__init__.py
stimulus/typing/protocols.py
stimulus/utils/__init__.py
stimulus/utils/generic_utils.py
stimulus/utils/model_file_interface.py
stimulus_py-0.5.1.dist-info/METADATA
stimulus_py-0.5.1.dist-info/WHEEL
stimulus_py-0.5.1.dist-info/entry_points.txt
stimulus_py-0.5.1.dist-info/licenses/LICENSE
stimulus_py-0.5.1.dist-info/RECORD
