Metadata-Version: 2.1
Name: stimulus-py
Version: 0.5.1
Summary: A package for testing deep learning models
Author: Alessio Vignoli, Suzanne Jin, Luisa Santus
Author-Email: Mathys Grapotte <mathysgrapotte@gmail.com>
License: MIT
Classifier: Development Status :: 4 - Beta
Classifier: Intended Audience :: Developers
Classifier: Programming Language :: Python
Classifier: Programming Language :: Python :: 3
Classifier: Programming Language :: Python :: 3 :: Only
Classifier: Programming Language :: Python :: 3.10
Classifier: Programming Language :: Python :: 3.11
Classifier: Programming Language :: Python :: 3.12
Classifier: Topic :: Documentation
Classifier: Topic :: Software Development
Classifier: Topic :: Utilities
Classifier: Typing :: Typed
Project-URL: Homepage, https://mathysgrapotte.github.io/stimulus-py
Project-URL: Documentation, https://mathysgrapotte.github.io/stimulus-py
Project-URL: Changelog, https://mathysgrapotte.github.io/stimulus-py/changelog
Project-URL: Repository, https://github.com/mathysgrapotte/stimulus-py
Project-URL: Issues, https://github.com/mathysgrapotte/stimulus-py/issues
Project-URL: Discussions, https://github.com/mathysgrapotte/stimulus-py/discussions
Project-URL: Gitter, https://gitter.im/stimulus-py/community
Project-URL: Funding, https://github.com/sponsors/mathysgrapotte
Requires-Python: <3.13,>=3.10
Requires-Dist: matplotlib>=3.9.0
Requires-Dist: multiprocess==0.70.16
Requires-Dist: numpy>=2.0.0
Requires-Dist: pandas>=2.2.0
Requires-Dist: polars>=1.26.0
Requires-Dist: pydantic>=2.7.0
Requires-Dist: safetensors>=0.4.5
Requires-Dist: scikit-learn>=1.5.0
Requires-Dist: scipy>=1.15.1
Requires-Dist: syrupy>=4.8.0
Requires-Dist: torch>=2.3.1
Requires-Dist: optuna>=4.0.0
Requires-Dist: click>=8.1.0
Requires-Dist: importlib_metadata
Requires-Dist: datasets>=3.6.0
Requires-Dist: transformers>=4.52.4
Requires-Dist: peft>=0.15.2
Requires-Dist: huggingface-hub>=0.32.0
Requires-Dist: evaluate>=0.4.3
Requires-Dist: hatchling>=1.27.0
